[
    {
        "title": "Golden Hour",
        "artist": "JVKE",
        "mp3": "https://files.catbox.moe/9a7kkk.mp3",
        "thumbnail": "https://i.scdn.co/image/ab67616d0000b2730af4476af141051c728ee8b9",
        "releaseDate": "2022-10-03",
        "duration": "3:29"
    },
    {
        "title": "Littleroot Town",
        "artist": "Pokemon",
        "mp3": "https://files.catbox.moe/7bzwfz.mp3",
        "thumbnail": "https://files.catbox.moe/5g3j1a.jpg",
        "releaseDate": "2019-11-29",
        "duration": "3:20"
    },
    {
        "title": "3:03 PM",
        "artist": "しゃろう Sharou",
        "mp3": "https://files.catbox.moe/kk06is.mp3",
        "thumbnail": "https://files.catbox.moe/q1ezdn.jpg",
        "releaseDate": "2022-03-23",
        "duration": "2:20"
    }
]
